magnetocaloric/__init__.py
magnetocaloric/mcepy.py
magnetocaloric/MH_Interpolation/__init__.py
magnetocaloric/MH_Interpolation/interpol.py
magnetocaloric/mce_2D_Operations/MH_Pivoting.py
magnetocaloric/mce_2D_Operations/Msqr_HbyM.py
magnetocaloric/mce_2D_Operations/N_exponent.py
magnetocaloric/mce_2D_Operations/T_FWHM_RCP.py
magnetocaloric/mce_2D_Operations/__init__.py
magnetocaloric/mce_2D_Operations/arrott_plotting.py
magnetocaloric/mce_2D_Operations/color_marker.py
magnetocaloric/mce_2D_Operations/data_2d_operation.py
magnetocaloric/mce_2D_Operations/data_plotting.py
magnetocaloric/mce_2D_Operations/data_reading.py
magnetocaloric/mce_2D_Operations/data_writing.py
magnetocaloric/mce_2D_Operations/delSm_Pivoting.py
magnetocaloric/mce_2D_Operations/delSm_T.py
magnetocaloric/mce_2D_Operations/mag_sus.py
magnetocaloric/mce_3D_Distribution/__init__.py
magnetocaloric/mce_3D_Distribution/data_3d_plotting.py
magnetocaloric-1.7.1.dist-info/Licence.txt
magnetocaloric-1.7.1.dist-info/METADATA
magnetocaloric-1.7.1.dist-info/WHEEL
magnetocaloric-1.7.1.dist-info/top_level.txt
magnetocaloric-1.7.1.dist-info/RECORD
