Metadata-Version: 2.1
Name: magnetocaloric
Version: 1.7.1
Summary: Effective Approach To Calculate Magnetocaloric Effect Of Any Magnetic Material Using Python
Home-page: https://github.com/supratimdasinfo/magnetocaloric.mcepy
Author: Supratim Das
Author-email: supratim0707@gmail.com
License: MIT
Keywords: magnetocaloric,software,mcepy,magnetic,programming,code,python,supratim,das,physics
Classifier: Development Status :: 5 - Production/Stable
Classifier: Intended Audience :: Education
Classifier: Operating System :: Microsoft :: Windows :: Windows 10
Classifier: License :: OSI Approved :: MIT License
Classifier: Programming Language :: Python :: 3
License-File: Licence.txt
Requires-Dist: scipy
Requires-Dist: matplotlib
Requires-Dist: xlrd (==1.2.0)
Requires-Dist: openpyxl
Requires-Dist: XlsxWriter
Requires-Dist: numpy
